pyehr/__init__.py
pyehr/extract.py
pyehr/_core/io_funcs.py
pyehr/cprd_aurum/add_variable.py
pyehr-0.1.0.dist-info/licenses/LICENSE
test/test_extract.py
pyehr-0.1.0.dist-info/METADATA
pyehr-0.1.0.dist-info/WHEEL
pyehr-0.1.0.dist-info/top_level.txt
pyehr-0.1.0.dist-info/RECORD
