Metadata-Version: 2.4
Name: pyehr
Version: 0.1.0
Summary: A Python package for extract data from large EHR dataset.
Author-email: Yiran Zhang <yiran.zhang-12@postgrad.manchester.ac.uk>
License: MIT License
Project-URL: Homepage, https://github.com/YiranZhang1014/pyehr
Project-URL: Bug Tracker, https://github.com/YiranZhang1014/pyehr/issues
Keywords: EHR,data extraction,medical research,Python package
Classifier: Development Status :: 3 - Alpha
Classifier: Intended Audience :: Science/Research
Classifier: Topic :: Scientific/Engineering :: Medical Science Apps.
Classifier: License :: OSI Approved :: MIT License
Classifier: Programming Language :: Python :: 3.10
Classifier: Programming Language :: Python :: 3.11
Classifier: Programming Language :: Python :: 3.12
Requires-Python: >=3.10
License-File: LICENSE
Requires-Dist: pandas<3.0.0,>=2.0.0
Requires-Dist: dask>=2024.8.0
Dynamic: license-file
